Metadata-Version: 2.1
Name: stockout-regression
Version: 0.0.1
Summary: Regression models for analyzing stockout effects of product sales.
Home-page: UNKNOWN
Author: Aysu Demir, Alexandra Malaga
Author-email: aysu.demir@bse.edu, alexandra.malaga@bse.edu
License: UNKNOWN
Platform: UNKNOWN
Classifier: Programming Language :: Python :: 3
Classifier: License :: OSI Approved :: MIT License
Classifier: Operating System :: OS Independent
License-File: LICENSE.txt
